django_opalstack/__init__.py
django_opalstack/admin.py
django_opalstack/apps.py
django_opalstack/models.py
django_opalstack/urls.py
django_opalstack/views.py
django_opalstack/migrations/0001_initial.py
django_opalstack/migrations/0002_rename_value_token_key_alter_token_server.py
django_opalstack/migrations/0003_remove_token_server.py
django_opalstack/migrations/__init__.py
django_opalstack/static/django_opalstack/js/htmx.min.js
django_opalstack/templates/django_opalstack/base.html
django_opalstack/templates/django_opalstack/base_app.html
django_opalstack/templates/django_opalstack/token_detail.html
django_opalstack/templates/django_opalstack/token_list.html
django_opalstack/templates/django_opalstack/htmx/app_detail.html
django_opalstack/templates/django_opalstack/htmx/app_list.html
django_opalstack/templates/django_opalstack/htmx/domain_list.html
django_opalstack/templates/django_opalstack/htmx/server_list.html
django_opalstack/templates/django_opalstack/htmx/site_list.html
django_opalstack/templates/django_opalstack/htmx/token_detail.html
django_opalstack/templates/django_opalstack/htmx/token_list.html
django_opalstack/templates/django_opalstack/htmx/user_list.html
django_opalstack-0.1.0.dist-info/METADATA
django_opalstack-0.1.0.dist-info/WHEEL
django_opalstack-0.1.0.dist-info/licenses/LICENSE
django_opalstack-0.1.0.dist-info/RECORD
