Metadata-Version: 2.4
Name: django-opalstack
Version: 0.1.0
Summary: Django interface to Opalstack python API
Project-URL: Repository, https://github.com/andywar65/django-opalstack
Author-email: andywar65 <andy.war1965@gmail.com>
License: MIT License
License-File: LICENSE
Classifier: Framework :: Django
Classifier: Operating System :: OS Independent
Classifier: Programming Language :: Python :: 3 :: Only
Classifier: Programming Language :: Python :: 3.9
Classifier: Programming Language :: Python :: 3.10
Classifier: Programming Language :: Python :: 3.11
Classifier: Programming Language :: Python :: 3.12
Requires-Python: >=3.9
Requires-Dist: django>=4.2
Requires-Dist: opalstack
Requires-Dist: requests
Provides-Extra: dev
Requires-Dist: coverage; extra == 'dev'
Requires-Dist: environs[django]; extra == 'dev'
